sentiment_analysis_spanish/.DS_Store
sentiment_analysis_spanish/__init__.py
sentiment_analysis_spanish/sentiment_analysis.py
sentiment_analysis_spanish/test_sentiment_analysis.py
sentiment_analysis_spanish/saved_model/.DS_Store
sentiment_analysis_spanish/saved_model/classifier_naive_bayes_compressed.pbz2
sentiment_analysis_spanish/saved_model/ngram_vectorized_compressed.pbz2
sentiment_analysis_spanish-0.0.25.dist-info/LICENSE
sentiment_analysis_spanish-0.0.25.dist-info/METADATA
sentiment_analysis_spanish-0.0.25.dist-info/WHEEL
sentiment_analysis_spanish-0.0.25.dist-info/top_level.txt
sentiment_analysis_spanish-0.0.25.dist-info/RECORD
